[
  {
    "ablation": "no_sqi_filter_rhythm_features_mean",
    "feature_count": 12,
    "features": [
      "peak_count",
      "estimated_hr_bpm",
      "ibi_count",
      "mean_ibi_ms",
      "median_ibi_ms",
      "sdnn_ms",
      "rmssd_ms",
      "pnn50",
      "mean_hr_bpm",
      "std_hr_bpm",
      "cv_ibi",
      "sample_entropy"
    ],
    "aggregation": "mean",
    "threshold": 0.845,
    "segment_test": {
      "accuracy": 0.9530226119058607,
      "sensitivity": 0.8654688869412795,
      "specificity": 0.9617095899940579,
      "precision": 0.691607330454068,
      "f1": 0.7688315058716668,
      "auroc": 0.9409670364167615,
      "auprc": 0.7067915906610922,
      "tn": 66357,
      "fp": 2642,
      "fn": 921,
      "tp": 5925
    },
    "record_test": {
      "accuracy": 0.9506962739932254,
      "sensitivity": 0.8265895953757225,
      "specificity": 0.9692773691042839,
      "precision": 0.8011204481792717,
      "f1": 0.813655761024182,
      "auroc": 0.9520995340205051,
      "auprc": 0.8126039523820467,
      "tn": 4480,
      "fp": 142,
      "fn": 120,
      "tp": 572
    },
    "counts": {
      "train_segments": 636702,
      "val_segments": 96171,
      "test_segments": 75845,
      "val_records": 5768,
      "test_records": 5314
    },
    "sqi_filtering": false,
    "sqi_features": false,
    "quality_weighted_aggregation": false
  },
  {
    "ablation": "no_sqi_filter_all_features_mean",
    "feature_count": 17,
    "features": [
      "peak_count",
      "heart_band_energy_ratio",
      "signal_skewness",
      "template_correlation",
      "estimated_hr_bpm",
      "quality_score",
      "ibi_count",
      "mean_ibi_ms",
      "median_ibi_ms",
      "sdnn_ms",
      "rmssd_ms",
      "pnn50",
      "mean_hr_bpm",
      "std_hr_bpm",
      "cv_ibi",
      "sample_entropy",
      "signal_spectral_entropy"
    ],
    "aggregation": "mean",
    "threshold": 0.783,
    "segment_test": {
      "accuracy": 0.9455863933021293,
      "sensitivity": 0.8810984516505989,
      "specificity": 0.9519848113740779,
      "precision": 0.6454788657035848,
      "f1": 0.7451053054165895,
      "auroc": 0.9444578358638374,
      "auprc": 0.760213878588509,
      "tn": 65686,
      "fp": 3313,
      "fn": 814,
      "tp": 6032
    },
    "record_test": {
      "accuracy": 0.9412871659766654,
      "sensitivity": 0.8323699421965318,
      "specificity": 0.9575941151016876,
      "precision": 0.7461139896373057,
      "f1": 0.7868852459016394,
      "auroc": 0.9514648464368701,
      "auprc": 0.8108803774920862,
      "tn": 4426,
      "fp": 196,
      "fn": 116,
      "tp": 576
    },
    "counts": {
      "train_segments": 636702,
      "val_segments": 96171,
      "test_segments": 75845,
      "val_records": 5768,
      "test_records": 5314
    },
    "sqi_filtering": false,
    "sqi_features": true,
    "quality_weighted_aggregation": false
  },
  {
    "ablation": "sqi_filter_rhythm_features_mean",
    "feature_count": 12,
    "features": [
      "peak_count",
      "estimated_hr_bpm",
      "ibi_count",
      "mean_ibi_ms",
      "median_ibi_ms",
      "sdnn_ms",
      "rmssd_ms",
      "pnn50",
      "mean_hr_bpm",
      "std_hr_bpm",
      "cv_ibi",
      "sample_entropy"
    ],
    "aggregation": "mean",
    "threshold": 0.853,
    "segment_test": {
      "accuracy": 0.9543961715304494,
      "sensitivity": 0.8751481042654028,
      "specificity": 0.9622827833212965,
      "precision": 0.6978034955125177,
      "f1": 0.7764783180026281,
      "auroc": 0.9500137004140274,
      "auprc": 0.7104274623072928,
      "tn": 65288,
      "fp": 2559,
      "fn": 843,
      "tp": 5909
    },
    "record_test": {
      "accuracy": 0.951707225051877,
      "sensitivity": 0.8343023255813954,
      "specificity": 0.9692174290049859,
      "precision": 0.8016759776536313,
      "f1": 0.8176638176638177,
      "auroc": 0.954152571852046,
      "auprc": 0.8132364767595741,
      "tn": 4471,
      "fp": 142,
      "fn": 114,
      "tp": 574
    },
    "counts": {
      "train_segments": 622065,
      "val_segments": 93200,
      "test_segments": 74599,
      "val_records": 5742,
      "test_records": 5301
    },
    "sqi_filtering": true,
    "sqi_features": false,
    "quality_weighted_aggregation": false
  },
  {
    "ablation": "sqi_filter_all_features_mean",
    "feature_count": 17,
    "features": [
      "peak_count",
      "heart_band_energy_ratio",
      "signal_skewness",
      "template_correlation",
      "estimated_hr_bpm",
      "quality_score",
      "ibi_count",
      "mean_ibi_ms",
      "median_ibi_ms",
      "sdnn_ms",
      "rmssd_ms",
      "pnn50",
      "mean_hr_bpm",
      "std_hr_bpm",
      "cv_ibi",
      "sample_entropy",
      "signal_spectral_entropy"
    ],
    "aggregation": "mean",
    "threshold": 0.759,
    "segment_test": {
      "accuracy": 0.9429751069049183,
      "sensitivity": 0.8970675355450237,
      "specificity": 0.9475437381166448,
      "precision": 0.62988768718802,
      "f1": 0.7401026392961878,
      "auroc": 0.9541939376840154,
      "auprc": 0.7683142289872696,
      "tn": 64288,
      "fp": 3559,
      "fn": 695,
      "tp": 6057
    },
    "record_test": {
      "accuracy": 0.9369930201848707,
      "sensitivity": 0.8430232558139535,
      "specificity": 0.9510080208107522,
      "precision": 0.7196029776674938,
      "f1": 0.7764390896921017,
      "auroc": 0.9543050731249906,
      "auprc": 0.8142305880173374,
      "tn": 4387,
      "fp": 226,
      "fn": 108,
      "tp": 580
    },
    "counts": {
      "train_segments": 622065,
      "val_segments": 93200,
      "test_segments": 74599,
      "val_records": 5742,
      "test_records": 5301
    },
    "sqi_filtering": true,
    "sqi_features": true,
    "quality_weighted_aggregation": false
  },
  {
    "ablation": "sqi_filter_all_features_quality_weighted",
    "feature_count": 17,
    "features": [
      "peak_count",
      "heart_band_energy_ratio",
      "signal_skewness",
      "template_correlation",
      "estimated_hr_bpm",
      "quality_score",
      "ibi_count",
      "mean_ibi_ms",
      "median_ibi_ms",
      "sdnn_ms",
      "rmssd_ms",
      "pnn50",
      "mean_hr_bpm",
      "std_hr_bpm",
      "cv_ibi",
      "sample_entropy",
      "signal_spectral_entropy"
    ],
    "aggregation": "quality_weighted",
    "threshold": 0.763,
    "segment_test": {
      "accuracy": 0.9434442820949343,
      "sensitivity": 0.8966232227488151,
      "specificity": 0.9481038218344215,
      "precision": 0.6322715404699739,
      "f1": 0.7415936791817236,
      "auroc": 0.9541939376840154,
      "auprc": 0.7683142289872696,
      "tn": 64326,
      "fp": 3521,
      "fn": 698,
      "tp": 6054
    },
    "record_test": {
      "accuracy": 0.937370307489153,
      "sensitivity": 0.8430232558139535,
      "specificity": 0.9514415781487102,
      "precision": 0.7213930348258707,
      "f1": 0.7774798927613941,
      "auroc": 0.9542382750467586,
      "auprc": 0.8142174542278875,
      "tn": 4389,
      "fp": 224,
      "fn": 108,
      "tp": 580
    },
    "counts": {
      "train_segments": 622065,
      "val_segments": 93200,
      "test_segments": 74599,
      "val_records": 5742,
      "test_records": 5301
    },
    "sqi_filtering": true,
    "sqi_features": true,
    "quality_weighted_aggregation": true
  },
  {
    "ablation": "sqi_filter_quality_features_quality_weighted",
    "feature_count": 5,
    "features": [
      "heart_band_energy_ratio",
      "signal_skewness",
      "template_correlation",
      "quality_score",
      "signal_spectral_entropy"
    ],
    "aggregation": "quality_weighted",
    "threshold": 0.668,
    "segment_test": {
      "accuracy": 0.9045027413236102,
      "sensitivity": 0.6771327014218009,
      "specificity": 0.9271301605082023,
      "precision": 0.48045397225725095,
      "f1": 0.562085074993853,
      "auroc": 0.8920998617288955,
      "auprc": 0.57788052089834,
      "tn": 62903,
      "fp": 4944,
      "fn": 2180,
      "tp": 4572
    },
    "record_test": {
      "accuracy": 0.889266176193171,
      "sensitivity": 0.6031976744186046,
      "specificity": 0.9319314979406026,
      "precision": 0.5692729766803841,
      "f1": 0.5857445306986592,
      "auroc": 0.8462330295071058,
      "auprc": 0.6133656729777891,
      "tn": 4299,
      "fp": 314,
      "fn": 273,
      "tp": 415
    },
    "counts": {
      "train_segments": 622065,
      "val_segments": 93200,
      "test_segments": 74599,
      "val_records": 5742,
      "test_records": 5301
    },
    "sqi_filtering": true,
    "sqi_features": true,
    "quality_weighted_aggregation": true
  }
]